{"stats": [{"H": "Videos", "C": "24"}, {"H": "Books", "C": "1"}, {"H": "Types", "C": "1"}, {"H": "Narrators", "C": "1"}, {"H": "Duration", "C": "4 H"}, {"H": "Views", "C": "517"}], "poster": {"P": "Images/KSUBBU.jpg"}, "info": [{"H": "Name", "V": "subbiramaNian"}, {"H": "Born", "V": "10 Nov 1910"}, {"H": "Died", "V": "15 Feb 1974"}, {"H": "Wiki", "V": "\u0b95\u0bca\u0ba4\u0bcd\u0ba4\u0bae\u0b99\u0bcd\u0b95\u0bb2\u0bae\u0bcd_\u0b9a\u0bc1\u0baa\u0bcd\u0baa\u0bc1"}], "title": {"H": "Kothamangalam Subbu", "V": "kotthamaMgalam subbu", "I": "person-fill"}, "videos": [{"folder": [{"B": 2912, "books": [{"A": 103, "D": "25:38", "I": "XZNZTkTTsgs", "N": 102, "P": "1", "T": 1, "V": "39"}, {"A": 103, "D": "14:57", "I": "rsi9pPvDhPg", "N": 102, "P": "2", "T": 1, "V": "14"}, {"A": 103, "D": "16:35", "I": "FkSN0nO1Ihg", "N": 102, "P": "3", "T": 1, "V": "21"}, {"A": 103, "D": "19:00", "I": "0thxrRnsY3k", "N": 102, "P": "4", "T": 1, "V": "25"}, {"A": 103, "D": "14:02", "I": "juFQtnj-h4s", "N": 102, "P": "5", "T": 1, "V": "20"}, {"A": 103, "D": "15:58", "I": "yq2Ta8iStq8", "N": 102, "P": "6", "T": 1, "V": "20"}, {"A": 103, "D": "14:03", "I": "pDZLiLMA-fg", "N": 102, "P": "7", "T": 1, "V": "17"}, {"A": 103, "D": "14:30", "I": "dFPfzmUO-rY", "N": 102, "P": "8", "T": 1, "V": "13"}, {"A": 103, "D": "13:48", "I": "IKMAYExcYUI", "N": 102, "P": "9", "T": 1, "V": "12"}, {"A": 103, "D": "13:34", "I": "8s_BvoZD5_o", "N": 102, "P": "10", "T": 1, "V": "20"}, {"A": 103, "D": "9:40", "I": "vhD47uIPnNo", "N": 102, "P": "11", "T": 1, "V": "17"}, {"A": 103, "D": "7:07", "I": "c_59n1a72zE", "N": 102, "P": "12", "T": 1, "V": "21"}, {"A": 103, "D": "10:43", "I": "2tAnH34HghY", "N": 102, "P": "13", "T": 1, "V": "20"}, {"A": 103, "D": "11:21", "I": "c1v03XUTTRk", "N": 102, "P": "14", "T": 1, "V": "18"}, {"A": 103, "D": "12:55", "I": "usNhTd9Cnic", "N": 102, "P": "15", "T": 1, "V": "14"}, {"A": 103, "D": "12:31", "I": "WnO3iYwYE_A", "N": 102, "P": "16", "T": 1, "V": "18"}, {"A": 103, "D": "11:52", "I": "EpL8ufC7Z3I", "N": 102, "P": "17", "T": 1, "V": "21"}, {"A": 103, "D": "12:47", "I": "4w2d0ETzlgE", "N": 102, "P": "18", "T": 1, "V": "23"}, {"A": 103, "D": "13:16", "I": "dFPNDrx3drY", "N": 102, "P": "19", "T": 1, "V": "24"}, {"A": 103, "D": "8:45", "I": "XmEBnVJGo_8", "N": 102, "P": "20", "T": 1, "V": "12"}, {"A": 103, "D": "7:50", "I": "9dmsuZpDmf0", "N": 102, "P": "21", "T": 1, "V": "21"}, {"A": 103, "D": "9:54", "I": "O5bZwyH4Qz8", "N": 102, "P": "22", "T": 1, "V": "21"}, {"A": 103, "D": "10:59", "I": "-Dwz4C4cvSQ", "N": 102, "P": "23", "T": 1, "V": "41"}, {"A": 103, "D": "2:08", "I": "OzbKpvxBcu0", "N": 102, "P": "", "T": 1, "V": "45"}]}]}]}