{"stats": [{"H": "Videos", "C": "1"}, {"H": "Types", "C": "1"}, {"H": "Authors", "C": "1"}, {"H": "Narrators", "C": "1"}, {"H": "Duration", "C": "1 M"}, {"H": "Views", "C": "225"}], "info": [{"H": "Author", "V": "Sivasankari", "P": "sivasaMkari", "I": 28}], "title": {"T": 72, "H": "Amma", "V": "ammA", "I": "book"}, "books": [{"I": "jHgNt7aO7gc", "T": 1, "B": 72, "P": "", "A": 28, "N": 0, "D": "1:53", "V": "225", "J": "m"}], "folders": [["author", 28, "0"]], "languages": {"english": "0", "tamil": "0"}}