{"stats": [{"H": "Videos", "C": "2"}, {"H": "Types", "C": "1"}, {"H": "Authors", "C": "1"}, {"H": "Narrators", "C": "1"}, {"H": "Duration", "C": "2 H"}, {"H": "Views", "C": "3 K"}], "info": [{"H": "Author", "V": "Lakshmi", "P": "lakshmi"}], "title": {"H": "Anjana Purinthukondal", "V": "aMjanA purinthukoNDAL", "I": "solid-book"}, "videos": [{"folder": [{"A": 3, "books": [{"B": 1172, "D": "1:03:47", "I": "N9NuO0UX_gg", "N": 0, "P": "", "T": 1, "V": "292"}, {"B": 1172, "D": "1:05:21", "I": "IvT0fZ18FdI", "N": 0, "P": "", "T": 1, "V": "2,176"}]}]}]}