{"stats": [{"H": "Videos", "C": "1"}, {"H": "Types", "C": "1"}, {"H": "Authors", "C": "1"}, {"H": "Narrators", "C": "1"}, {"H": "Duration", "C": "38 M"}, {"H": "Views", "C": "130"}], "info": [{"H": "Author", "V": "Akilan", "P": "akilan", "I": 80}], "title": {"T": 3621, "H": "Chitthira Paavai", "V": "citthirap pAvai", "I": "book"}, "books": [{"I": "SkWgpqoUM5I", "T": 1, "B": 3621, "P": "", "A": 80, "N": 0, "D": "38:34", "V": "130", "J": "m"}], "folders": [["author", 80, "0"]], "languages": {"english": "0", "tamil": "0"}}