{"stats": [{"H": "Videos", "C": "1"}, {"H": "Types", "C": "1"}, {"H": "Authors", "C": "1"}, {"H": "Narrators", "C": "1"}, {"H": "Duration", "C": "46 M"}, {"H": "Views", "C": "3 K"}], "info": [{"H": "Type", "V": "Crime Novel", "P": "kuTRap pudhinam"}, {"H": "Author", "V": "Rajesh Kumar", "P": "rAjEs kumAr"}], "title": {"H": "Edu Ayudam", "V": "eDu Ayudam", "I": "solid-book"}, "videos": [{"folder": [{"A": 97, "books": [{"B": 2826, "D": "46:12", "I": "C2IKHLWF8Pk", "N": 77, "P": "", "T": 5, "V": "2,057"}]}]}]}