{"stats": [{"H": "Videos", "C": "3"}, {"H": "Types", "C": "1"}, {"H": "Authors", "C": "1"}, {"H": "Narrators", "C": "3"}, {"H": "Duration", "C": "27 M"}, {"H": "Views", "C": "9 K"}], "info": [{"H": "Type", "V": "Short Story", "P": "siRukadhai", "I": 2}, {"H": "Author", "V": "Ki. Rajanarayanan", "P": "ki. rAja.NArAyaNan", "I": 16}], "title": {"T": 1856, "H": "Ezhuda Maranda Kadai", "V": "ezhuda maRanda kadai", "I": "book"}, "books": [{"I": "5ihucCL5j2k", "T": 2, "B": 1856, "P": "29", "A": 16, "N": 21, "D": "11:25", "V": "8,204", "J": "h"}, {"I": "6V5bIf64Goc", "T": 2, "B": 1856, "P": "", "A": 16, "N": 53, "D": "8:35", "V": "83", "J": "m"}, {"I": "TEBu5J5w14A", "T": 2, "B": 1856, "P": "", "A": 16, "N": 0, "D": "8:14", "V": "55", "J": "h"}], "folders": [["author", 16, "0,1,2"]], "languages": {"english": "0", "tamil": "0"}}