{"stats": [{"H": "Videos", "C": "2"}, {"H": "Types", "C": "1"}, {"H": "Authors", "C": "1"}, {"H": "Narrators", "C": "1"}, {"H": "Duration", "C": "36 M"}, {"H": "Views", "C": "5 K"}], "info": [{"H": "Type", "V": "Short Story", "P": "siRukadhai"}, {"H": "Author", "V": "Jayakanthan", "P": "jeyakAnthan"}], "title": {"H": "Idhu Enna Periya Vishayam", "V": "idhu enna periya vishayam", "I": "solid-book"}, "videos": [{"folder": [{"A": 7, "books": [{"B": 1073, "D": "18:52", "I": "IPc4Ld9mur8", "J": "h", "N": 0, "P": "", "T": 2, "V": "881"}, {"B": 1073, "D": "18:09", "I": "MKPoXW-nPEI", "J": "h", "N": 0, "P": "", "T": 2, "V": "3,139"}]}]}]}