{"stats": [{"H": "Videos", "C": "17"}, {"H": "Types", "C": "1"}, {"H": "Authors", "C": "1"}, {"H": "Narrators", "C": "1"}, {"H": "Duration", "C": "5 H"}, {"H": "Views", "C": "12 K"}], "info": [{"H": "Type", "V": "Historical Novel", "P": "varalATRup pudhinam"}, {"H": "Author", "V": "Sandilyan", "P": "sAMDilyan"}], "title": {"H": "Jeeva Bhoomi", "V": "jIva bhUmi", "I": "solid-book"}, "videos": [{"folder": [{"A": 4, "books": [{"B": 101, "D": "19:41", "I": "OhDZnmqXdm8", "J": "h", "N": 28, "P": "1", "T": 4, "V": "2,495"}, {"B": 101, "D": "9:28", "I": "RUjTkq7SWBA", "J": "h", "N": 28, "P": "2", "T": 4, "V": "539"}, {"B": 101, "D": "18:40", "I": "AXChv3yBWa8", "J": "h", "N": 28, "P": "3", "T": 4, "V": "907"}, {"B": 101, "D": "11:16", "I": "SGYtn1QPcDU", "J": "h", "N": 28, "P": "4", "T": 4, "V": "526"}, {"B": 101, "D": "14:41", "I": "BEKsi543FwA", "J": "h", "N": 28, "P": "5", "T": 4, "V": "359"}, {"B": 101, "D": "21:50", "I": "BgdC9_JCwHA", "J": "h", "N": 28, "P": "6,7", "T": 4, "V": "403"}, {"B": 101, "D": "20:56", "I": "eI0kha1ngN4", "J": "h", "N": 28, "P": "8,9", "T": 4, "V": "622"}, {"B": 101, "D": "19:25", "I": "cxc87NMRb-M", "J": "h", "N": 28, "P": "10,11", "T": 4, "V": "457"}, {"B": 101, "D": "11:46", "I": "QMAw5gC3zVc", "J": "h", "N": 28, "P": "12", "T": 4, "V": "381"}, {"B": 101, "D": "25:34", "I": "JbNAa8_I0lM", "J": "h", "N": 28, "P": "13,14", "T": 4, "V": "452"}, {"B": 101, "D": "17:26", "I": "5x5cYyZ5HMA", "J": "h", "N": 28, "P": "15,16", "T": 4, "V": "428"}, {"B": 101, "D": "18:05", "I": "AraJgLbQLII", "J": "h", "N": 28, "P": "17,18", "T": 4, "V": "512"}, {"B": 101, "D": "17:56", "I": "P1h_J7kx-Ek", "J": "h", "N": 28, "P": "19", "T": 4, "V": "497"}, {"B": 101, "D": "25:25", "I": "8STfw7HecWQ", "J": "h", "N": 28, "P": "20,21", "T": 4, "V": "640"}, {"B": 101, "D": "30:35", "I": "Qk2DFZU1VH8", "J": "h", "N": 28, "P": "22,23", "T": 4, "V": "575"}, {"B": 101, "D": "24:09", "I": "7xJzqOVH0EI", "J": "h", "N": 28, "P": "24,25", "T": 4, "V": "785"}, {"B": 101, "D": "13:52", "I": "r86mYe4qTEw", "J": "h", "N": 28, "P": "26", "T": 4, "V": "544"}]}]}]}