{"stats": [{"H": "Videos", "C": "4"}, {"H": "Types", "C": "1"}, {"H": "Authors", "C": "1"}, {"H": "Narrators", "C": "2"}, {"H": "Duration", "C": "40 M"}, {"H": "Views", "C": "757"}], "info": [{"H": "Type", "V": "Short Story", "P": "siRukadhai"}, {"H": "Author", "V": "Ra. Ki. Rangarajan", "P": "rA. ki. raMgarAjan"}], "title": {"H": "Kanna Pinna Kadhaigal", "V": "kannA pinnA kadhaigaL", "I": "solid-book"}, "videos": [{"folder": [{"A": 31, "books": [{"B": 1744, "D": "8:39", "I": "16llpXlra3U", "N": 47, "P": "", "T": 2, "V": "354"}, {"B": 1744, "D": "11:01", "I": "fPb3KHwqyEo", "N": 47, "P": "", "T": 2, "V": "71"}, {"B": 1744, "D": "9:44", "I": "KwVS0t-9As4", "N": 47, "P": "", "T": 2, "V": "41"}, {"B": 1744, "D": "12:11", "I": "MQcNM-E4NrE", "N": 0, "P": "", "T": 2, "V": "291"}]}]}]}