{"stats": [{"H": "Videos", "C": "19"}, {"H": "Types", "C": "1"}, {"H": "Authors", "C": "1"}, {"H": "Narrators", "C": "2"}, {"H": "Duration", "C": "6 H"}, {"H": "Views", "C": "3 K"}], "info": [{"H": "Author", "V": "Sujatha", "P": "sujAtA"}], "title": {"H": "Karaiyellam Shenbagapoo", "V": "karaiyellAm seNbagappU", "I": "solid-book"}, "videos": [{"folder": [{"A": 8, "books": [{"B": 593, "D": "21:54", "I": "ew4qzVX_1z8", "J": "h", "N": 68, "P": "8,10", "T": 1, "V": "74"}, {"B": 593, "D": "14:17", "I": "8a6yK7HiLbk", "J": "h", "N": 68, "P": "20,21", "T": 1, "V": "75"}, {"B": 593, "D": "22:51", "I": "xYn5rYqixGc", "J": "h", "N": 68, "P": "17,19", "T": 1, "V": "52"}, {"B": 593, "D": "20:45", "I": "krk9BPqQvCU", "J": "h", "N": 68, "P": "14,16", "T": 1, "V": "51"}, {"B": 593, "D": "21:41", "I": "NwKiNeWBuuM", "J": "h", "N": 68, "P": "11,13", "T": 1, "V": "74"}, {"B": 593, "D": "16:34", "I": "Qn6Zqfpd6UE", "J": "h", "N": 68, "P": "5,7", "T": 1, "V": "75"}, {"B": 593, "D": "19:06", "I": "flaRBQBYX8g", "J": "m", "N": 68, "P": "2,4", "T": 1, "V": "90"}, {"B": 593, "D": "11:16", "I": "mUf79_Rt6G8", "J": "h", "N": 68, "P": "1", "T": 1, "V": "182"}, {"B": 593, "D": "26:19", "I": "uCpTDbC0XbY", "J": "m", "N": 19, "P": "2", "T": 1, "V": "169"}, {"B": 593, "D": "26:19", "I": "WTnDHc8i8Fw", "J": "m", "N": 19, "P": "1", "T": 1, "V": "280"}, {"B": 593, "D": "24:10", "I": "-k8fo2mPMto", "J": "m", "N": 19, "P": "3", "T": 1, "V": "163"}, {"B": 593, "D": "28:36", "I": "mR_0eoRLnJo", "J": "m", "N": 19, "P": "7", "T": 1, "V": "117"}, {"B": 593, "D": "27:06", "I": "W8m1MaenYtw", "J": "m", "N": 19, "P": "4", "T": 1, "V": "139"}, {"B": 593, "D": "20:19", "I": "PzjceE41I6Y", "J": "m", "N": 19, "P": "6", "T": 1, "V": "125"}, {"B": 593, "D": "13:42", "I": "EmsKtHUO9BU", "J": "m", "N": 19, "P": "11", "T": 1, "V": "93"}, {"B": 593, "D": "25:05", "I": "fUA-yaenPDw", "J": "m", "N": 19, "P": "8", "T": 1, "V": "103"}, {"B": 593, "D": "23:46", "I": "xVNF63bO4po", "J": "m", "N": 19, "P": "9", "T": 1, "V": "114"}, {"B": 593, "D": "26:14", "I": "o28N62Rz4EI", "J": "m", "N": 19, "P": "5", "T": 1, "V": "131"}, {"B": 593, "D": "23:46", "I": "AxZeamIKaSA", "J": "m", "N": 19, "P": "10", "T": 1, "V": "112"}]}]}]}