{"stats": [{"H": "Videos", "C": "9"}, {"H": "Types", "C": "1"}, {"H": "Authors", "C": "1"}, {"H": "Narrators", "C": "3"}, {"H": "Duration", "C": "2 H"}, {"H": "Views", "C": "7 K"}], "info": [{"H": "Type", "V": "Novella", "P": "kuRuGkadhai"}, {"H": "Author", "V": "Sujatha", "P": "sujAtA"}], "title": {"H": "Maayaa", "V": "mAyA", "I": "book"}, "videos": [{"folder": [{"A": 8, "books": [{"B": 65, "D": "21:19", "I": "fP2L-7i2LXg", "J": "m", "N": 19, "P": "1", "T": 3, "V": "242"}, {"B": 65, "D": "16:58", "I": "DrY_nNCsARw", "J": "h", "N": 7, "P": "1,5", "T": 3, "V": "1,809"}, {"B": 65, "D": "18:57", "I": "ipVzhKBCAAM", "J": "m", "N": 19, "P": "2", "T": 3, "V": "185"}, {"B": 65, "D": "13:25", "I": "H1QVxNm-2wI", "J": "h", "N": 7, "P": "2,5", "T": 3, "V": "1,088"}, {"B": 65, "D": "16:23", "I": "MK8v4YaSAII", "J": "m", "N": 19, "P": "3", "T": 3, "V": "145"}, {"B": 65, "D": "10:31", "I": "SyrpS9mCO9o", "J": "h", "N": 7, "P": "3,5", "T": 3, "V": "998"}, {"B": 65, "D": "13:46", "I": "AucluPDQGq8", "J": "h", "N": 7, "P": "4,5", "T": 3, "V": "1,012"}, {"B": 65, "D": "21:26", "I": "FFFz77GpSxc", "J": "h", "N": 7, "P": "5", "T": 3, "V": "1,028"}, {"B": 65, "D": "4:03", "I": "NvbWNYY2M2U", "J": "m", "N": 0, "P": "", "T": 3, "V": "227"}]}]}]}