{"stats": [{"H": "Videos", "C": "5"}, {"H": "Types", "C": "1"}, {"H": "Authors", "C": "1"}, {"H": "Narrators", "C": "1"}, {"H": "Duration", "C": "1 H"}, {"H": "Views", "C": "7 K"}], "info": [{"H": "Author", "V": "Lakshmi", "P": "lakshmi"}], "title": {"H": "Mogathirai", "V": "mOgatthirai", "I": "solid-book"}, "videos": [{"folder": [{"A": 3, "books": [{"B": 1166, "D": "21:29", "I": "2q_s1uqxio0", "N": 0, "P": "1", "T": 1, "V": "3,100"}, {"B": 1166, "D": "15:15", "I": "bmo4cEzcKjc", "N": 0, "P": "2", "T": 1, "V": "1,200"}, {"B": 1166, "D": "13:55", "I": "km4mzdc9RQU", "N": 0, "P": "3", "T": 1, "V": "1,000"}, {"B": 1166, "D": "9:39", "I": "UTPDKv-xtKY", "N": 0, "P": "4", "T": 1, "V": "1,600"}, {"B": 1166, "D": "48:33", "I": "cRYE-MI51cc", "N": 0, "P": "", "T": 1, "V": "62"}]}]}]}