{"stats": [{"H": "Videos", "C": "5"}, {"H": "Types", "C": "1"}, {"H": "Authors", "C": "1"}, {"H": "Narrators", "C": "1"}, {"H": "Duration", "C": "4 H"}, {"H": "Views", "C": "2 K"}], "info": [{"H": "Type", "V": "Crime Novel", "P": "kuTRap pudhinam"}, {"H": "Author", "V": "Rajesh Kumar", "P": "rAjEsh kumAr"}], "title": {"H": "Oru Adigalai Kolai", "V": "oru adigAlai kolai", "I": "solid-book"}, "videos": [{"folder": [{"A": 97, "books": [{"B": 3060, "D": "25:17", "I": "FB7L4wwLtmA", "N": 0, "P": "1", "T": 5, "V": "390"}, {"B": 3060, "D": "25:21", "I": "4RHrKSbZeZA", "N": 0, "P": "2", "T": 5, "V": "183"}, {"B": 3060, "D": "27:39", "I": "6QCnRBkfFWE", "N": 0, "P": "3", "T": 5, "V": "183"}, {"B": 3060, "D": "26:08", "I": "aYvbB6bkK7g", "N": 0, "P": "4", "T": 5, "V": "211"}, {"B": 3060, "D": "2:22:42", "I": "1f5KfKlkx4Y", "N": 0, "P": "", "T": 5, "V": "830"}]}]}]}