{"stats": [{"H": "Videos", "C": "1"}, {"H": "Types", "C": "1"}, {"H": "Authors", "C": "1"}, {"H": "Narrators", "C": "1"}, {"H": "Duration", "C": "11 M"}, {"H": "Views", "C": "111"}], "info": [{"H": "Type", "V": "Short Story", "P": "siRukadhai"}, {"H": "Author", "V": "Sujatha", "P": "sujAtA"}], "title": {"H": "Oru Periya Manitharum Pickpocketum", "V": "oru periya manidarum pikpAkkeTTum", "I": "book"}, "books": [{"I": "j-LtAY88hBk", "T": 2, "B": 1412, "P": "", "A": 8, "N": 0, "D": "11:10", "V": "111", "J": "h"}], "folders": [["author", 8, "0"]], "languages": {"english": "0", "tamil": "0"}}