{"stats": [{"H": "Videos", "C": "1"}, {"H": "Types", "C": "1"}, {"H": "Authors", "C": "1"}, {"H": "Narrators", "C": "1"}, {"H": "Duration", "C": "13 M"}, {"H": "Views", "C": "340"}], "info": [{"H": "Type", "V": "Short Story", "P": "siRukadhai"}, {"H": "Author", "V": "Devan", "P": "dEvan"}], "title": {"H": "Rangoon Periyappa", "V": "raMgUn periyappA", "I": "book"}, "videos": [{"folder": [{"A": 11, "books": [{"B": 1123, "D": "13:32", "I": "eM_wHBJIqIw", "J": "h", "N": 48, "P": "", "T": 2, "V": "340"}]}]}]}