{"stats": [{"H": "Videos", "C": "2"}, {"H": "Types", "C": "1"}, {"H": "Authors", "C": "1"}, {"H": "Narrators", "C": "2"}, {"H": "Duration", "C": "27 M"}, {"H": "Views", "C": "214"}], "info": [{"H": "Type", "V": "Short Story", "P": "siRukadhai"}, {"H": "Author", "V": "Vallikannan", "P": "vallikkaNNan"}], "title": {"H": "Sirappu Parisu", "V": "siRappu parisu", "I": "book"}, "videos": [{"folder": [{"A": 24, "books": [{"B": 2051, "D": "13:45", "I": "woR5iLglGgU", "J": "m", "N": 53, "P": "", "T": 2, "V": "30"}, {"B": 2051, "D": "14:08", "I": "HI_o8L4vCmU", "J": "m", "N": 0, "P": "", "T": 2, "V": "184"}]}]}]}