{"stats": [{"H": "Videos", "C": "3"}, {"H": "Types", "C": "1"}, {"H": "Authors", "C": "1"}, {"H": "Narrators", "C": "2"}, {"H": "Duration", "C": "42 M"}, {"H": "Views", "C": "336"}], "info": [{"H": "Type", "V": "Short Story", "P": "siRukadhai"}, {"H": "Author", "V": "Sundara Ramaswamy", "P": "suMdara rAmasAmi"}], "title": {"H": "Stamp Album", "V": "sTamp Albam", "I": "solid-book"}, "videos": [{"folder": [{"A": 22, "books": [{"B": 1301, "D": "15:29", "I": "tAWRURSWyPY", "J": "m", "N": 0, "P": "", "T": 2, "V": "311"}, {"B": 1301, "D": "13:42", "I": "EuPUno-CT5M", "J": "h", "N": 36, "P": "", "T": 2, "V": "19"}, {"B": 1301, "D": "14:46", "I": "uExvMzFPPNw", "J": "m", "N": 0, "P": "", "T": 2, "V": "6"}]}]}]}