{"stats": [{"H": "Videos", "C": "4"}, {"H": "Types", "C": "1"}, {"H": "Authors", "C": "1"}, {"H": "Narrators", "C": "4"}, {"H": "Duration", "C": "44 M"}, {"H": "Views", "C": "6 K"}], "info": [{"H": "Type", "V": "Short Story", "P": "siRukadhai"}, {"H": "Author", "V": "Ku. Pa. Rajagopalan", "P": "ku. pa. rAjagOpAlan"}], "title": {"H": "Thirai", "V": "thirai", "I": "solid-book"}, "videos": [{"folder": [{"A": 88, "books": [{"B": 1816, "D": "10:27", "I": "y9IpJfJl9lY", "J": "h", "N": 68, "P": "", "T": 2, "V": "74"}, {"B": 1816, "D": "14:26", "I": "cAZh6OgVzWo", "J": "m", "N": 21, "P": "98", "T": 2, "V": "4,917"}, {"B": 1816, "D": "11:25", "I": "n6en6kWvmiI", "J": "h", "N": 36, "P": "", "T": 2, "V": "4"}, {"B": 1816, "D": "9:48", "I": "UWmiCLttMno", "J": "m", "N": 6, "P": "", "T": 2, "V": "124"}]}]}]}