{"stats": [{"H": "Videos", "C": "1"}, {"H": "Types", "C": "1"}, {"H": "Authors", "C": "1"}, {"H": "Narrators", "C": "1"}, {"H": "Duration", "C": "14 M"}, {"H": "Views", "C": "24 K"}], "info": [{"H": "Type", "V": "Short Story", "P": "siRukadhai"}, {"H": "Author", "V": "Vannadasan", "P": "vaNNadhAsan"}], "title": {"T": 763, "H": "Ulpuram Vazhiyum Tuligal", "V": "uLpuRam vazhiyum tuLigaL", "I": "book"}, "books": [{"I": "FN90nV51l6s", "T": 2, "B": 763, "P": "", "A": 42, "N": 1, "D": "14:03", "V": "23,488", "J": "m"}], "folders": [["author", 42, "0"]], "languages": {"english": "0", "tamil": "0"}}