{"stats": [{"H": "Videos", "C": "4"}, {"H": "Types", "C": "1"}, {"H": "Authors", "C": "1"}, {"H": "Narrators", "C": "2"}, {"H": "Duration", "C": "1 H"}, {"H": "Views", "C": "10 K"}], "info": [{"H": "Type", "V": "Short Story", "P": "siRukadhai", "I": 2}, {"H": "Author", "V": "Sujatha", "P": "sujAtA", "I": 8}], "title": {"T": 1210, "H": "Vandavan", "V": "vandavan", "I": "book"}, "books": [{"I": "L9zBjHyPZ2o", "T": 2, "B": 1210, "P": "", "A": 8, "N": 111, "D": "8:44", "V": "1,586", "J": "m"}, {"I": "P8sDPN9h0Yk", "T": 2, "B": 1210, "P": "", "A": 8, "N": 111, "D": "11:38", "V": "558", "J": "m"}, {"I": "gi8sTsTf5rs", "T": 2, "B": 1210, "P": "", "A": 8, "N": 111, "D": "1:20:12", "V": "7,324", "J": "m"}, {"I": "ukbe8YZ3Gco", "T": 2, "B": 1210, "P": "", "A": 8, "N": 0, "D": "14:56", "V": "281", "J": "h"}], "folders": [["author", 8, "0,1,2,3"]], "languages": {"english": "0", "tamil": "0"}}