{"stats": [{"H": "Videos", "C": "7"}, {"H": "Types", "C": "1"}, {"H": "Authors", "C": "1"}, {"H": "Narrators", "C": "1"}, {"H": "Duration", "C": "1 H"}, {"H": "Views", "C": "516"}], "info": [{"H": "Type", "V": "Short Story", "P": "siRukadhai"}, {"H": "Author", "V": "Jeyamohan", "P": "jeyamOgan"}], "title": {"H": "Vazhvile Orumurai", "V": "vAzhvilE oru muRai", "I": "solid-book"}, "videos": [{"folder": [{"A": 5, "books": [{"B": 3051, "D": "9:55", "I": "PMETQCEwE-Q", "J": "h", "N": 18, "P": "", "T": 2, "V": "75"}, {"B": 3051, "D": "19:28", "I": "6_2-XC6px-8", "J": "m", "N": 18, "P": "", "T": 2, "V": "67"}, {"B": 3051, "D": "12:06", "I": "iBPgkg36qLU", "J": "m", "N": 18, "P": "", "T": 2, "V": "132"}, {"B": 3051, "D": "13:47", "I": "kF3dlVkbc3g", "J": "m", "N": 18, "P": "", "T": 2, "V": "48"}, {"B": 3051, "D": "11:49", "I": "Ny570fRIizQ", "J": "m", "N": 18, "P": "", "T": 2, "V": "57"}, {"B": 3051, "D": "11:23", "I": "OG8fGrKnfxs", "J": "m", "N": 18, "P": "", "T": 2, "V": "80"}, {"B": 3051, "D": "3:41", "I": "QkCZwdOSS4Y", "J": "m", "N": 18, "P": "", "T": 2, "V": "57"}]}]}]}