{"stats": [{"H": "Videos", "C": "1"}, {"H": "Types", "C": "1"}, {"H": "Authors", "C": "1"}, {"H": "Narrators", "C": "1"}, {"H": "Duration", "C": "59 M"}, {"H": "Views", "C": "792"}], "info": [{"H": "Type", "V": "Short Story", "P": "siRukadhai"}, {"H": "Author", "V": "Kalki Krishnamurthy", "P": "kalki"}, {"H": "Read", "V": [["siRukadhaigaL", "http://www.sirukathaigal.com/\u0b95\u0bc1\u0b9f\u0bc1\u0bae\u0bcd\u0baa\u0bae\u0bcd/\u0b9c\u0bae\u0bc0\u0ba9\u0bcd\u0ba4\u0bbe\u0bb0\u0bcd-\u0bae\u0b95\u0ba9\u0bcd/"]], "P": [["siRukadhaigaL", "http://www.sirukathaigal.com/\u0b95\u0bc1\u0b9f\u0bc1\u0bae\u0bcd\u0baa\u0bae\u0bcd/\u0b9c\u0bae\u0bc0\u0ba9\u0bcd\u0ba4\u0bbe\u0bb0\u0bcd-\u0bae\u0b95\u0ba9\u0bcd/"]]}], "title": {"H": "Zamindar Magan", "V": "jami.ndAr magan", "I": "book"}, "books": [{"I": "vDd7wbbGO_A", "T": 2, "B": 919, "P": "", "A": 1, "N": 0, "D": "59:57", "V": "792", "J": "h"}], "folders": [["author", 1, "0"]], "languages": {"english": "0", "tamil": "0"}}